reverse/ezFPGA/attachments/src/encryptor.sv
module Encryptor#(
    parameter logic [7:0] FLAG [0:13] = {
        "A", "C", "T", "F", "{", "t", "e", "s", "t", "f", "l", "a", "g", "}"
    }
)(
    input rst,
    input clk,
    output logic [7:0] cypher
);

    typedef logic [7:0] uint8_t;
    localparam l = $size(FLAG);

    uint8_t aa [38:0];

    genvar i;
    generate
        for(i = 0; i < l; i++) begin : gen
            assign aa[i] = FLAG[i];
        end
        for (i = l; i < 39; i++) begin : gen
            assign aa[i] = 0;
        end
    endgenerate

    uint8_t ab [0:3] = {11,4,5,14};
    uint8_t ac [35:0];

    generate
        for(i = 0; i < 36; i++) begin : gen
            assign ac[i] = aa[i]*ab[0] + aa[i+1]*ab[1] + aa[i+2]*ab[2] + aa[i+3]*ab[3];
        end
    endgenerate

    uint8_t ad [0:35] = {116,174,193,124,102,100,11,193,115,4,127,139,98,214,197,145,97,151,31,30,117,15,230,179,235,25,244,202,73,222,15,191,119,140,94,32};
    
    uint8_t ae [35:0];

    generate
        for (i = 0; i < 36; i = i + 1) begin
            assign ae[i] = ac[i/6*6]*ad[i%6]+ac[i/6*6+1]*ad[i%6+6]+ac[i/6*6+2]*ad[i%6+12]+ac[i/6*6+3]*ad[i%6+18]+ac[i/6*6+4]*ad[i%6+24]+ac[i/6*6+5]*ad[i%6+30];
        end
    endgenerate

    uint8_t af[35:0];
    uint8_t ba[255:0];
    uint8_t ca,cb,cd,ce,cf,cg,ch;
    uint8_t da;
    uint8_t db[0:7] = {"e","c","l","i","p","s","k","y"};
    typedef enum logic[1:0] {S0,S1,S2,S3} state_t;
    state_t state;

    assign cd = ca + 1;
    assign ce = cb + ba[cd];
    assign cf = ba[cd] + ba[ce];
    assign ch = cg + ba[da] + db[da%8];

    always_ff @( posedge clk or posedge rst) begin
        if (rst) begin
            ca <= 0;
            cb <= 0;
            cg <= 0;
            da <= 0;
            cypher <= 0;
            state <= S1;
        end else begin
            case (state)
                S0: begin
                    if (da != 8'd255) begin
                        ba[da] <= da;
                        da <= da + 1;
                    end else begin
                        ba[da] <= da;
                        da <= 0;
                        state <= S1;
                    end
                end
                S1: begin
                    if (da != 8'd255) begin
                        ba[da] <= ba[ch];
                        ba[ch] <= ba[da];
                        cg <= ch;
                        da <= da + 1;
                    end else begin
                        ba[da] <= ba[ch];
                        ba[ch] <= ba[da];
                        da <= 0;
                        state <= S2;
                    end
                end
                S2: begin
                    if (da < 36) begin
                        ba[cd] <= ba[ce];
                        ba[ce] <= ba[cd];
                        af[da[5:0]] <= ba[cf] + ae[da[5:0]];
                        ca <= cd;
                        cb <= ce;
                        da <= da + 1;
                    end else begin
                        da <= 0;
                        state <= S3;
                    end
                end
                S3: begin
                    if (da < 36) begin
                        cypher <= af[da[5:0]];
                        da <= da + 1;
                    end else begin
                        cypher <= 0;
                    end
                end
            endcase
        end
    end




endmodule

reverse/ezFPGA/attachments/sim/testbench.v
`timescale 1ns/1ps
module Testbench(
    output logic [7:0] cypher
);

    logic rst;
    logic clk;

    Encryptor dut(
        .rst(rst),
        .clk(clk),
        .cypher(cypher)
    );

    initial begin
        clk = 1'b0;
        rst = 1'b1;
        #10;
        rst = 1'b0;
    end

    always begin
        clk = ~clk;
        #5;
    end

    reg [31:0] cycle_count = 0;
    always @(posedge clk) begin
        cycle_count <= cycle_count + 1;
        if (cycle_count >= 1000) begin
            $display("Reached max cycle count %d", cycle_count);
            $finish;
        end
    end

    always begin
        if (cypher != 0) begin
            $display("%02x", cypher);
        end
    end

    initial begin
        $dumpfile("../Testbench.vcd");
        $dumpvars(0,dut);
        $dumpon;
    end
        
endmodule

reverse/ezFPGA/attachments/Testbench.vcd
$version Generated by VerilatedVcd $end
$timescale 1ps $end
 $scope module TOP $end
  $var wire 8 # cypher [7:0] $end
  $scope module Testbench $end
   $var wire 8 # cypher [7:0] $end
   $var wire 1 $ rst $end
   $var wire 1 % clk $end
   $var wire 32 & cycle_count [31:0] $end
  $upscope $end
 $upscope $end
$enddefinitions $end


#0
b00000000 #
1$
1%
b00000000000000000000000000000000 &
#5000
0%
#10000
0$
1%
b00000000000000000000000000000001 &
#15000
0%
#20000
1%
b00000000000000000000000000000010 &
#25000
0%
#30000
1%
b00000000000000000000000000000011 &
#35000
0%
#40000
1%
b00000000000000000000000000000100 &
#45000
0%
#50000
1%
b00000000000000000000000000000101 &
#55000
0%
#60000
1%
b00000000000000000000000000000110 &
#65000
0%
#70000
1%
b00000000000000000000000000000111 &
#75000
0%
#80000
1%
b00000000000000000000000000001000 &
#85000
0%
#90000
1%
b00000000000000000000000000001001 &
#95000
0%
#100000
1%
b00000000000000000000000000001010 &
#105000
0%
#110000
1%
b00000000000000000000000000001011 &
#115000
0%
#120000
1%
b00000000000000000000000000001100 &
#125000
0%
#130000
1%
b00000000000000000000000000001101 &
#135000
0%
#140000
1%
b00000000000000000000000000001110 &
#145000
0%
#150000
1%
b00000000000000000000000000001111 &
#155000
0%
#160000
1%
b00000000000000000000000000010000 &
#165000
0%
#170000
1%
b00000000000000000000000000010001 &
#175000
0%
#180000
1%
b00000000000000000000000000010010 &
#185000
0%
#190000
1%
b00000000000000000000000000010011 &
#195000
0%
#200000
1%
b00000000000000000000000000010100 &
#205000
0%
#210000
1%
b00000000000000000000000000010101 &
#215000
0%
#220000
1%
b00000000000000000000000000010110 &
#225000
0%
#230000
1%
b00000000000000000000000000010111 &
#235000
0%
#240000
1%
b00000000000000000000000000011000 &
#245000
0%
#250000
1%
b00000000000000000000000000011001 &
#255000
0%
#260000
1%
b00000000000000000000000000011010 &
#265000
0%
#270000
1%
b00000000000000000000000000011011 &
#275000
0%
#280000
1%
b00000000000000000000000000011100 &
#285000
0%
#290000
1%
b00000000000000000000000000011101 &
#295000
0%
#300000
1%
b00000000000000000000000000011110 &
#305000
0%
#310000
1%
b00000000000000000000000000011111 &
#315000
0%
#320000
1%
b00000000000000000000000000100000 &
#325000
0%
#330000
1%
b00000000000000000000000000100001 &
#335000
0%
#340000
1%
b00000000000000000000000000100010 &
#345000
0%
#350000
1%
b00000000000000000000000000100011 &
#355000
0%
#360000
1%
b00000000000000000000000000100100 &
#365000
0%
#370000
1%
b00000000000000000000000000100101 &
#375000
0%
#380000
1%
b00000000000000000000000000100110 &
#385000
0%
#390000
1%
b00000000000000000000000000100111 &
#395000
0%
#400000
1%
b00000000000000000000000000101000 &
#405000
0%
#410000
1%
b00000000000000000000000000101001 &
#415000
0%
#420000
1%
b00000000000000000000000000101010 &
#425000
0%
#430000
1%
b00000000000000000000000000101011 &
#435000
0%
#440000
1%
b00000000000000000000000000101100 &
#445000
0%
#450000
1%
b00000000000000000000000000101101 &
#455000
0%
#460000
1%
b00000000000000000000000000101110 &
#465000
0%
#470000
1%
b00000000000000000000000000101111 &
#475000
0%
#480000
1%
b00000000000000000000000000110000 &
#485000
0%
#490000
1%
b00000000000000000000000000110001 &
#495000
0%
#500000
1%
b00000000000000000000000000110010 &
#505000
0%
#510000
1%
b00000000000000000000000000110011 &
#515000
0%
#520000
1%
b00000000000000000000000000110100 &
#525000
0%
#530000
1%
b00000000000000000000000000110101 &
#535000
0%
#540000
1%
b00000000000000000000000000110110 &
#545000
0%
#550000
1%
b00000000000000000000000000110111 &
#555000
0%
#560000
1%
b00000000000000000000000000111000 &
#565000
0%
#570000
1%
b00000000000000000000000000111001 &
#575000
0%
#580000
1%
b00000000000000000000000000111010 &
#585000
0%
#590000
1%
b00000000000000000000000000111011 &
#595000
0%
#600000
1%
b00000000000000000000000000111100 &
#605000
0%
#610000
1%
b00000000000000000000000000111101 &
#615000
0%
#620000
1%
b00000000000000000000000000111110 &
#625000
0%
#630000
1%
b00000000000000000000000000111111 &
#635000
0%
#640000
1%
b00000000000000000000000001000000 &
#645000
0%
#650000
1%
b00000000000000000000000001000001 &
#655000
0%
#660000
1%
b00000000000000000000000001000010 &
#665000
0%
#670000
1%
b00000000000000000000000001000011 &
#675000
0%
#680000
1%
b00000000000000000000000001000100 &
#685000
0%
#690000
1%
b00000000000000000000000001000101 &
#695000
0%
#700000
1%
b00000000000000000000000001000110 &
#705000
0%
#710000
1%
b00000000000000000000000001000111 &
#715000
0%
#720000
1%
b00000000000000000000000001001000 &
#725000
0%
#730000
1%
b00000000000000000000000001001001 &
#735000
0%
#740000
1%
b00000000000000000000000001001010 &
#745000
0%
#750000
1%
b00000000000000000000000001001011 &
#755000
0%
#760000
1%
b00000000000000000000000001001100 &
#765000
0%
#770000
1%
b00000000000000000000000001001101 &
#775000
0%
#780000
1%
b00000000000000000000000001001110 &
#785000
0%
#790000
1%
b00000000000000000000000001001111 &
#795000
0%
#800000
1%
b00000000000000000000000001010000 &
#805000
0%
#810000
1%
b00000000000000000000000001010001 &
#815000
0%
#820000
1%
b00000000000000000000000001010010 &
#825000
0%
#830000
1%
b00000000000000000000000001010011 &
#835000
0%
#840000
1%
b00000000000000000000000001010100 &
#845000
0%
#850000
1%
b00000000000000000000000001010101 &
#855000
0%
#860000
1%
b00000000000000000000000001010110 &
#865000
0%
#870000
1%
b00000000000000000000000001010111 &
#875000
0%
#880000
1%
b00000000000000000000000001011000 &
#885000
0%
#890000
1%
b00000000000000000000000001011001 &
#895000
0%
#900000
1%
b00000000000000000000000001011010 &
#905000
0%
#910000
1%
b00000000000000000000000001011011 &
#915000
0%
#920000
1%
b00000000000000000000000001011100 &
#925000
0%
#930000
1%
b00000000000000000000000001011101 &
#935000
0%
#940000
1%
b00000000000000000000000001011110 &
#945000
0%
#950000
1%
b00000000000000000000000001011111 &
#955000
0%
#960000
1%
b00000000000000000000000001100000 &
#965000
0%
#970000
1%
b00000000000000000000000001100001 &
#975000
0%
#980000
1%
b00000000000000000000000001100010 &
#985000
0%
#990000
1%
b00000000000000000000000001100011 &
#995000
0%
#1000000
1%
b00000000000000000000000001100100 &
#1005000
0%
#1010000
1%
b00000000000000000000000001100101 &
#1015000
0%
#1020000
1%
b00000000000000000000000001100110 &
#1025000
0%
#1030000
1%
b00000000000000000000000001100111 &
#1035000
0%
#1040000
1%
b00000000000000000000000001101000 &
#1045000
0%
#1050000
1%
b00000000000000000000000001101001 &
#1055000
0%
#1060000
1%
b00000000000000000000000001101010 &
#1065000
0%
#1070000
1%
b00000000000000000000000001101011 &
#1075000
0%
#1080000
1%
b00000000000000000000000001101100 &
#1085000
0%
#1090000
1%
b00000000000000000000000001101101 &
#1095000
0%
#1100000
1%
b00000000000000000000000001101110 &
#1105000
0%
#1110000
1%
b00000000000000000000000001101111 &
#1115000
0%
#1120000
1%
b00000000000000000000000001110000 &
#1125000
0%
#1130000
1%
b00000000000000000000000001110001 &
#1135000
0%
#1140000
1%
b00000000000000000000000001110010 &
#1145000
0%
#1150000
1%
b00000000000000000000000001110011 &
#1155000
0%
#1160000
1%
b00000000000000000000000001110100 &
#1165000
0%
#1170000
1%
b00000000000000000000000001110101 &
#1175000
0%
#1180000
1%
b00000000000000000000000001110110 &
#1185000
0%
#1190000
1%
b00000000000000000000000001110111 &
#1195000
0%
#1200000
1%
b00000000000000000000000001111000 &
#1205000
0%
#1210000
1%
b00000000000000000000000001111001 &
#1215000
0%
#1220000
1%
b00000000000000000000000001111010 &
#1225000
0%
#1230000
1%
b00000000000000000000000001111011 &
#1235000
0%
#1240000
1%
b00000000000000000000000001111100 &
#1245000
0%
#1250000
1%
b00000000000000000000000001111101 &
#1255000
0%
#1260000
1%
b00000000000000000000000001111110 &
#1265000
0%
#1270000
1%
b00000000000000000000000001111111 &
#1275000
0%
#1280000
1%
b00000000000000000000000010000000 &
#1285000
0%
#1290000
1%
b00000000000000000000000010000001 &
#1295000
0%
#1300000
1%
b00000000000000000000000010000010 &
#1305000
0%
#1310000
1%
b00000000000000000000000010000011 &
#1315000
0%
#1320000
1%
b00000000000000000000000010000100 &
#1325000
0%
#1330000
1%
b00000000000000000000000010000101 &
#1335000
0%
#1340000
1%
b00000000000000000000000010000110 &
#1345000
0%
#1350000
1%
b00000000000000000000000010000111 &
#1355000
0%
#1360000
1%
b00000000000000000000000010001000 &
#1365000
0%
#1370000
1%
b00000000000000000000000010001001 &
#1375000
0%
#1380000
1%
b00000000000000000000000010001010 &
#1385000
0%
#1390000
1%
b00000000000000000000000010001011 &
#1395000
0%
#1400000
1%
b00000000000000000000000010001100 &
#1405000
0%
#1410000
1%
b00000000000000000000000010001101 &
#1415000
0%
#1420000
1%
b00000000000000000000000010001110 &
#1425000
0%
#1430000
1%
b00000000000000000000000010001111 &
#1435000
0%
#1440000
1%
b00000000000000000000000010010000 &
#1445000
0%
#1450000
1%
b00000000000000000000000010010001 &
#1455000
0%
#1460000
1%
b00000000000000000000000010010010 &
#1465000
0%
#1470000
1%
b00000000000000000000000010010011 &
#1475000
0%
#1480000
1%
b00000000000000000000000010010100 &
#1485000
0%
#1490000
1%
b00000000000000000000000010010101 &
#1495000
0%
#1500000
1%
b00000000000000000000000010010110 &
#1505000
0%
#1510000
1%
b00000000000000000000000010010111 &
#1515000
0%
#1520000
1%
b00000000000000000000000010011000 &
#1525000
0%
#1530000
1%
b00000000000000000000000010011001 &
#1535000
0%
#1540000
1%
b00000000000000000000000010011010 &
#1545000
0%
#1550000
1%
b00000000000000000000000010011011 &
#1555000
0%
#1560000
1%
b00000000000000000000000010011100 &
#1565000
0%
#1570000
1%
b00000000000000000000000010011101 &
#1575000
0%
#1580000
1%
b00000000000000000000000010011110 &
#1585000
0%
#1590000
1%
b00000000000000000000000010011111 &
#1595000
0%
#1600000
1%
b00000000000000000000000010100000 &
#1605000
0%
#1610000
1%
b00000000000000000000000010100001 &
#1615000
0%
#1620000
1%
b00000000000000000000000010100010 &
#1625000
0%
#1630000
1%
b00000000000000000000000010100011 &
#1635000
0%
#1640000
1%
b00000000000000000000000010100100 &
#1645000
0%
#1650000
1%
b00000000000000000000000010100101 &
#1655000
0%
#1660000
1%
b00000000000000000000000010100110 &
#1665000
0%
#1670000
1%
b00000000000000000000000010100111 &
#1675000
0%
#1680000
1%
b00000000000000000000000010101000 &
#1685000
0%
#1690000
1%
b00000000000000000000000010101001 &
#1695000
0%
#1700000
1%
b00000000000000000000000010101010 &
#1705000
0%
#1710000
1%
b00000000000000000000000010101011 &
#1715000
0%
#1720000
1%
b00000000000000000000000010101100 &
#1725000
0%
#1730000
1%
b00000000000000000000000010101101 &
#1735000
0%
#1740000
1%
b00000000000000000000000010101110 &
#1745000
0%
#1750000
1%
b00000000000000000000000010101111 &
#1755000
0%
#1760000
1%
b00000000000000000000000010110000 &
#1765000
0%
#1770000
1%
b00000000000000000000000010110001 &
#1775000
0%
#1780000
1%
b00000000000000000000000010110010 &
#1785000
0%
#1790000
1%
b00000000000000000000000010110011 &
#1795000
0%
#1800000
1%
b00000000000000000000000010110100 &
#1805000
0%
#1810000
1%
b00000000000000000000000010110101 &
#1815000
0%
#1820000
1%
b00000000000000000000000010110110 &
#1825000
0%
#1830000
1%
b00000000000000000000000010110111 &
#1835000
0%
#1840000
1%
b00000000000000000000000010111000 &
#1845000
0%
#1850000
1%
b00000000000000000000000010111001 &
#1855000
0%
#1860000
1%
b00000000000000000000000010111010 &
#1865000
0%
#1870000
1%
b00000000000000000000000010111011 &
#1875000
0%
#1880000
1%
b00000000000000000000000010111100 &
#1885000
0%
#1890000
1%
b00000000000000000000000010111101 &
#1895000
0%
#1900000
1%
b00000000000000000000000010111110 &
#1905000
0%
#1910000
1%
b00000000000000000000000010111111 &
#1915000
0%
#1920000
1%
b00000000000000000000000011000000 &
#1925000
0%
#1930000
1%
b00000000000000000000000011000001 &
#1935000
0%
#1940000
1%
b00000000000000000000000011000010 &
#1945000
0%
#1950000
1%
b00000000000000000000000011000011 &
#1955000
0%
#1960000
1%
b00000000000000000000000011000100 &
#1965000
0%
#1970000
1%
b00000000000000000000000011000101 &
#1975000
0%
#1980000
1%
b00000000000000000000000011000110 &
#1985000
0%
#1990000
1%
b00000000000000000000000011000111 &
#1995000
0%
#2000000
1%
b00000000000000000000000011001000 &
#2005000
0%
#2010000
1%
b00000000000000000000000011001001 &
#2015000
0%
#2020000
1%
b00000000000000000000000011001010 &
#2025000
0%
#2030000
1%
b00000000000000000000000011001011 &
#2035000
0%
#2040000
1%
b00000000000000000000000011001100 &
#2045000
0%
#2050000
1%
b00000000000000000000000011001101 &
#2055000
0%
#2060000
1%
b00000000000000000000000011001110 &
#2065000
0%
#2070000
1%
b00000000000000000000000011001111 &
#2075000
0%
#2080000
1%
b00000000000000000000000011010000 &
#2085000
0%
#2090000
1%
b00000000000000000000000011010001 &
#2095000
0%
#2100000
1%
b00000000000000000000000011010010 &
#2105000
0%
#2110000
1%
b00000000000000000000000011010011 &
#2115000
0%
#2120000
1%
b00000000000000000000000011010100 &
#2125000
0%
#2130000
1%
b00000000000000000000000011010101 &
#2135000
0%
#2140000
1%
b00000000000000000000000011010110 &
#2145000
0%
#2150000
1%
b00000000000000000000000011010111 &
#2155000
0%
#2160000
1%
b00000000000000000000000011011000 &
#2165000
0%
#2170000
1%
b00000000000000000000000011011001 &
#2175000
0%
#2180000
1%
b00000000000000000000000011011010 &
#2185000
0%
#2190000
1%
b00000000000000000000000011011011 &
#2195000
0%
#2200000
1%
b00000000000000000000000011011100 &
#2205000
0%
#2210000
1%
b00000000000000000000000011011101 &
#2215000
0%
#2220000
1%
b00000000000000000000000011011110 &
#2225000
0%
#2230000
1%
b00000000000000000000000011011111 &
#2235000
0%
#2240000
1%
b00000000000000000000000011100000 &
#2245000
0%
#2250000
1%
b00000000000000000000000011100001 &
#2255000
0%
#2260000
1%
b00000000000000000000000011100010 &
#2265000
0%
#2270000
1%
b00000000000000000000000011100011 &
#2275000
0%
#2280000
1%
b00000000000000000000000011100100 &
#2285000
0%
#2290000
1%
b00000000000000000000000011100101 &
#2295000
0%
#2300000
1%
b00000000000000000000000011100110 &
#2305000
0%
#2310000
1%
b00000000000000000000000011100111 &
#2315000
0%
#2320000
1%
b00000000000000000000000011101000 &
#2325000
0%
#2330000
1%
b00000000000000000000000011101001 &
#2335000
0%
#2340000
1%
b00000000000000000000000011101010 &
#2345000
0%
#2350000
1%
b00000000000000000000000011101011 &
#2355000
0%
#2360000
1%
b00000000000000000000000011101100 &
#2365000
0%
#2370000
1%
b00000000000000000000000011101101 &
#2375000
0%
#2380000
1%
b00000000000000000000000011101110 &
#2385000
0%
#2390000
1%
b00000000000000000000000011101111 &
#2395000
0%
#2400000
1%
b00000000000000000000000011110000 &
#2405000
0%
#2410000
1%
b00000000000000000000000011110001 &
#2415000
0%
#2420000
1%
b00000000000000000000000011110010 &
#2425000
0%
#2430000
1%
b00000000000000000000000011110011 &
#2435000
0%
#2440000
1%
b00000000000000000000000011110100 &
#2445000
0%
#2450000
1%
b00000000000000000000000011110101 &
#2455000
0%
#2460000
1%
b00000000000000000000000011110110 &
#2465000
0%
#2470000
1%
b00000000000000000000000011110111 &
#2475000
0%
#2480000
1%
b00000000000000000000000011111000 &
#2485000
0%
#2490000
1%
b00000000000000000000000011111001 &
#2495000
0%
#2500000
1%
b00000000000000000000000011111010 &
#2505000
0%
#2510000
1%
b00000000000000000000000011111011 &
#2515000
0%
#2520000
1%
b00000000000000000000000011111100 &
#2525000
0%
#2530000
1%
b00000000000000000000000011111101 &
#2535000
0%
#2540000
1%
b00000000000000000000000011111110 &
#2545000
0%
#2550000
1%
b00000000000000000000000011111111 &
#2555000
0%
#2560000
1%
b00000000000000000000000100000000 &
#2565000
0%
#2570000
1%
b00000000000000000000000100000001 &
#2575000
0%
#2580000
1%
b00000000000000000000000100000010 &
#2585000
0%
#2590000
1%
b00000000000000000000000100000011 &
#2595000
0%
#2600000
1%
b00000000000000000000000100000100 &
#2605000
0%
#2610000
1%
b00000000000000000000000100000101 &
#2615000
0%
#2620000
1%
b00000000000000000000000100000110 &
#2625000
0%
#2630000
1%
b00000000000000000000000100000111 &
#2635000
0%
#2640000
1%
b00000000000000000000000100001000 &
#2645000
0%
#2650000
1%
b00000000000000000000000100001001 &
#2655000
0%
#2660000
1%
b00000000000000000000000100001010 &
#2665000
0%
#2670000
1%
b00000000000000000000000100001011 &
#2675000
0%
#2680000
1%
b00000000000000000000000100001100 &
#2685000
0%
#2690000
1%
b00000000000000000000000100001101 &
#2695000
0%
#2700000
1%
b00000000000000000000000100001110 &
#2705000
0%
#2710000
1%
b00000000000000000000000100001111 &
#2715000
0%
#2720000
1%
b00000000000000000000000100010000 &
#2725000
0%
#2730000
1%
b00000000000000000000000100010001 &
#2735000
0%
#2740000
1%
b00000000000000000000000100010010 &
#2745000
0%
#2750000
1%
b00000000000000000000000100010011 &
#2755000
0%
#2760000
1%
b00000000000000000000000100010100 &
#2765000
0%
#2770000
1%
b00000000000000000000000100010101 &
#2775000
0%
#2780000
1%
b00000000000000000000000100010110 &
#2785000
0%
#2790000
1%
b00000000000000000000000100010111 &
#2795000
0%
#2800000
1%
b00000000000000000000000100011000 &
#2805000
0%
#2810000
1%
b00000000000000000000000100011001 &
#2815000
0%
#2820000
1%
b00000000000000000000000100011010 &
#2825000
0%
#2830000
1%
b00000000000000000000000100011011 &
#2835000
0%
#2840000
1%
b00000000000000000000000100011100 &
#2845000
0%
#2850000
1%
b00000000000000000000000100011101 &
#2855000
0%
#2860000
1%
b00000000000000000000000100011110 &
#2865000
0%
#2870000
1%
b00000000000000000000000100011111 &
#2875000
0%
#2880000
1%
b00000000000000000000000100100000 &
#2885000
0%
#2890000
1%
b00000000000000000000000100100001 &
#2895000
0%
#2900000
1%
b00000000000000000000000100100010 &
#2905000
0%
#2910000
1%
b00000000000000000000000100100011 &
#2915000
0%
#2920000
1%
b00000000000000000000000100100100 &
#2925000
0%
#2930000
1%
b00000000000000000000000100100101 &
#2935000
0%
#2940000
1%
b00000000000000000000000100100110 &
#2945000
0%
#2950000
1%
b00000000000000000000000100100111 &
#2955000
0%
#2960000
1%
b00000000000000000000000100101000 &
#2965000
0%
#2970000
1%
b00000000000000000000000100101001 &
#2975000
0%
#2980000
1%
b00000000000000000000000100101010 &
#2985000
0%
#2990000
1%
b00000000000000000000000100101011 &
#2995000
0%
#3000000
1%
b00000000000000000000000100101100 &
#3005000
0%
#3010000
1%
b00000000000000000000000100101101 &
#3015000
0%
#3020000
1%
b00000000000000000000000100101110 &
#3025000
0%
#3030000
1%
b00000000000000000000000100101111 &
#3035000
0%
#3040000
1%
b00000000000000000000000100110000 &
#3045000
0%
#3050000
1%
b00000000000000000000000100110001 &
#3055000
0%
#3060000
1%
b00000000000000000000000100110010 &
#3065000
0%
#3070000
1%
b00000000000000000000000100110011 &
#3075000
0%
#3080000
1%
b00000000000000000000000100110100 &
#3085000
0%
#3090000
1%
b00000000000000000000000100110101 &
#3095000
0%
#3100000
1%
b00000000000000000000000100110110 &
#3105000
0%
#3110000
1%
b00000000000000000000000100110111 &
#3115000
0%
#3120000
1%
b00000000000000000000000100111000 &
#3125000
0%
#3130000
1%
b00000000000000000000000100111001 &
#3135000
0%
#3140000
1%
b00000000000000000000000100111010 &
#3145000
0%
#3150000
1%
b00000000000000000000000100111011 &
#3155000
0%
#3160000
1%
b00000000000000000000000100111100 &
#3165000
0%
#3170000
1%
b00000000000000000000000100111101 &
#3175000
0%
#3180000
1%
b00000000000000000000000100111110 &
#3185000
0%
#3190000
1%
b00000000000000000000000100111111 &
#3195000
0%
#3200000
1%
b00000000000000000000000101000000 &
#3205000
0%
#3210000
1%
b00000000000000000000000101000001 &
#3215000
0%
#3220000
1%
b00000000000000000000000101000010 &
#3225000
0%
#3230000
1%
b00000000000000000000000101000011 &
#3235000
0%
#3240000
1%
b00000000000000000000000101000100 &
#3245000
0%
#3250000
1%
b00000000000000000000000101000101 &
#3255000
0%
#3260000
1%
b00000000000000000000000101000110 &
#3265000
0%
#3270000
1%
b00000000000000000000000101000111 &
#3275000
0%
#3280000
1%
b00000000000000000000000101001000 &
#3285000
0%
#3290000
1%
b00000000000000000000000101001001 &
#3295000
0%
#3300000
1%
b00000000000000000000000101001010 &
#3305000
0%
#3310000
1%
b00000000000000000000000101001011 &
#3315000
0%
#3320000
1%
b00000000000000000000000101001100 &
#3325000
0%
#3330000
1%
b00000000000000000000000101001101 &
#3335000
0%
#3340000
1%
b00000000000000000000000101001110 &
#3345000
0%
#3350000
1%
b00000000000000000000000101001111 &
#3355000
0%
#3360000
1%
b00000000000000000000000101010000 &
#3365000
0%
#3370000
1%
b00000000000000000000000101010001 &
#3375000
0%
#3380000
1%
b00000000000000000000000101010010 &
#3385000
0%
#3390000
1%
b00000000000000000000000101010011 &
#3395000
0%
#3400000
1%
b00000000000000000000000101010100 &
#3405000
0%
#3410000
1%
b00000000000000000000000101010101 &
#3415000
0%
#3420000
1%
b00000000000000000000000101010110 &
#3425000
0%
#3430000
1%
b00000000000000000000000101010111 &
#3435000
0%
#3440000
1%
b00000000000000000000000101011000 &
#3445000
0%
#3450000
1%
b00000000000000000000000101011001 &
#3455000
0%
#3460000
1%
b00000000000000000000000101011010 &
#3465000
0%
#3470000
1%
b00000000000000000000000101011011 &
#3475000
0%
#3480000
1%
b00000000000000000000000101011100 &
#3485000
0%
#3490000
1%
b00000000000000000000000101011101 &
#3495000
0%
#3500000
1%
b00000000000000000000000101011110 &
#3505000
0%
#3510000
1%
b00000000000000000000000101011111 &
#3515000
0%
#3520000
1%
b00000000000000000000000101100000 &
#3525000
0%
#3530000
1%
b00000000000000000000000101100001 &
#3535000
0%
#3540000
1%
b00000000000000000000000101100010 &
#3545000
0%
#3550000
1%
b00000000000000000000000101100011 &
#3555000
0%
#3560000
1%
b00000000000000000000000101100100 &
#3565000
0%
#3570000
1%
b00000000000000000000000101100101 &
#3575000
0%
#3580000
1%
b00000000000000000000000101100110 &
#3585000
0%
#3590000
1%
b00000000000000000000000101100111 &
#3595000
0%
#3600000
1%
b00000000000000000000000101101000 &
#3605000
0%
#3610000
1%
b00000000000000000000000101101001 &
#3615000
0%
#3620000
1%
b00000000000000000000000101101010 &
#3625000
0%
#3630000
1%
b00000000000000000000000101101011 &
#3635000
0%
#3640000
1%
b00000000000000000000000101101100 &
#3645000
0%
#3650000
1%
b00000000000000000000000101101101 &
#3655000
0%
#3660000
1%
b00000000000000000000000101101110 &
#3665000
0%
#3670000
1%
b00000000000000000000000101101111 &
#3675000
0%
#3680000
1%
b00000000000000000000000101110000 &
#3685000
0%
#3690000
1%
b00000000000000000000000101110001 &
#3695000
0%
#3700000
1%
b00000000000000000000000101110010 &
#3705000
0%
#3710000
1%
b00000000000000000000000101110011 &
#3715000
0%
#3720000
1%
b00000000000000000000000101110100 &
#3725000
0%
#3730000
1%
b00000000000000000000000101110101 &
#3735000
0%
#3740000
1%
b00000000000000000000000101110110 &
#3745000
0%
#3750000
1%
b00000000000000000000000101110111 &
#3755000
0%
#3760000
1%
b00000000000000000000000101111000 &
#3765000
0%
#3770000
1%
b00000000000000000000000101111001 &
#3775000
0%
#3780000
1%
b00000000000000000000000101111010 &
#3785000
0%
#3790000
1%
b00000000000000000000000101111011 &
#3795000
0%
#3800000
1%
b00000000000000000000000101111100 &
#3805000
0%
#3810000
1%
b00000000000000000000000101111101 &
#3815000
0%
#3820000
1%
b00000000000000000000000101111110 &
#3825000
0%
#3830000
1%
b00000000000000000000000101111111 &
#3835000
0%
#3840000
1%
b00000000000000000000000110000000 &
#3845000
0%
#3850000
1%
b00000000000000000000000110000001 &
#3855000
0%
#3860000
1%
b00000000000000000000000110000010 &
#3865000
0%
#3870000
1%
b00000000000000000000000110000011 &
#3875000
0%
#3880000
1%
b00000000000000000000000110000100 &
#3885000
0%
#3890000
1%
b00000000000000000000000110000101 &
#3895000
0%
#3900000
1%
b00000000000000000000000110000110 &
#3905000
0%
#3910000
1%
b00000000000000000000000110000111 &
#3915000
0%
#3920000
1%
b00000000000000000000000110001000 &
#3925000
0%
#3930000
1%
b00000000000000000000000110001001 &
#3935000
0%
#3940000
1%
b00000000000000000000000110001010 &
#3945000
0%
#3950000
1%
b00000000000000000000000110001011 &
#3955000
0%
#3960000
1%
b00000000000000000000000110001100 &
#3965000
0%
#3970000
1%
b00000000000000000000000110001101 &
#3975000
0%
#3980000
1%
b00000000000000000000000110001110 &
#3985000
0%
#3990000
1%
b00000000000000000000000110001111 &
#3995000
0%
#4000000
1%
b00000000000000000000000110010000 &
#4005000
0%
#4010000
1%
b00000000000000000000000110010001 &
#4015000
0%
#4020000
1%
b00000000000000000000000110010010 &
#4025000
0%
#4030000
1%
b00000000000000000000000110010011 &
#4035000
0%
#4040000
1%
b00000000000000000000000110010100 &
#4045000
0%
#4050000
1%
b00000000000000000000000110010101 &
#4055000
0%
#4060000
1%
b00000000000000000000000110010110 &
#4065000
0%
#4070000
1%
b00000000000000000000000110010111 &
#4075000
0%
#4080000
1%
b00000000000000000000000110011000 &
#4085000
0%
#4090000
1%
b00000000000000000000000110011001 &
#4095000
0%
#4100000
1%
b00000000000000000000000110011010 &
#4105000
0%
#4110000
1%
b00000000000000000000000110011011 &
#4115000
0%
#4120000
1%
b00000000000000000000000110011100 &
#4125000
0%
#4130000
1%
b00000000000000000000000110011101 &
#4135000
0%
#4140000
1%
b00000000000000000000000110011110 &
#4145000
0%
#4150000
1%
b00000000000000000000000110011111 &
#4155000
0%
#4160000
1%
b00000000000000000000000110100000 &
#4165000
0%
#4170000
1%
b00000000000000000000000110100001 &
#4175000
0%
#4180000
1%
b00000000000000000000000110100010 &
#4185000
0%
#4190000
1%
b00000000000000000000000110100011 &
#4195000
0%
#4200000
1%
b00000000000000000000000110100100 &
#4205000
0%
#4210000
1%
b00000000000000000000000110100101 &
#4215000
0%
#4220000
1%
b00000000000000000000000110100110 &
#4225000
0%
#4230000
1%
b00000000000000000000000110100111 &
#4235000
0%
